{
  "name": "Lucille Lane",
  "age": 20,
  "address": {
    "street": "Ukke Turnpike",
    "city": "Cogeghu",
    "state": "AK",
    "zip": "44817"
  },
  "contact": {
    "phone": "(743) 312-6188",
    "servicePhone": "800871451"
  },
  "birthday": "1984-06-16T02:35:07.828Z",
  "ip": "151.207.58.191",
  "foo": "bar",
  "profile": {
    "about": "Zew zes cucnet sofne fuodgu huwju hupek wavjat zafewef omovas iz hefilnu li ap mu. Ewomilse mogic wipok evecac zodepo racij piugve ansojif eto lem diviv ul rul numomo. Vanujod kutoz piok seneup mafek sat mukem zuspeho norepum eda nij no pazvofij teecmes zilasji bab. Goziwgob vupbud top egibew hiigewe luisiref dupus cib dickud paciju ijosi vosam vofa em. Vuk oh awvidbof gul kiemoze sinpor ceb hufgaho ofaha cu isnas retomu wartaj gip muiv.",
    "bio": "Pudal ektakdu kadobu vo bekmi aboop luf vuvoj joduv ne upsot wujudino wafez. Sis tuhgawaf la ju kepi tefihnan kem mojipmi ap paso gu tijavosu hek ak wunusoci hew nomava. Re ja ulezaw giglinag rait ecgek meemewu biezoon souzoc hagjosub to lac cu de daihe tamisic hoappe. Puejwo lo donnojfud nohili no ca lewivheh hezaruf worak meckahpu faksef cuh hajufvo ogodan ewota bobul gezan tamir. Tecahab sen bud buvlupo otjeg ipugosog wes ak ceubiso saloju girpair puklok. Bet samsat celizduj tipalofo jujuino jik wopabvo ojmus maapirap lafiwo wehzubfi zu go ocdu. Joz oliwo osdohuh nir tublu bovwub da icu vo luhojez egobi fedfa nazhawno ujfu wovaj abowujpo hola."
  },
  "apiKey": "2052bf6d927d8cba698c24c40371b4a7e80d5e620c47ea14658a0f6be9c0d553",
  "currency": {
    "code": "COP",
    "name": "Colombia Peso"
  }
}