{
  "name": "Joe Salazar",
  "age": 30,
  "address": {
    "street": "Awaac Turnpike",
    "city": "Fedeku",
    "state": "OK",
    "zip": "99555"
  },
  "contact": {
    "phone": "(214) 762-1876",
    "servicePhone": "800787851"
  },
  "birthday": "1989-12-16T20:52:27.405Z",
  "ip": "32.192.74.25",
  "foo": "bar",
  "profile": {
    "about": "Uri ot ufpuc ocup uri awa civtoum bucaf gecus pi kasikkid nukog rozut. Webwa ozis vige uzo lakkutcef rev gompehuh tetdoshuv le gegugetih cewsuw feesu. Ovu ijosih ekajanu zid mul zi uwude gulja opomi bobtarisi wor hehlif por. Bi gi no riliguhe ulaoc bedi fugutkuw le cackitob cawa goep dohrenuz meoc ibebir re. Baulukef zibizmas sokosuke ta rocforca geragop wi zeklaer ragup gonut muwuan kazhosjof regohepe ewno ituukajin. Decriza iko epubod bi huwdi tegfi zum ojfofiji ecenu kuzohze fawulfoj wah jejamof. Re pakli lupa cubrat gawgiil ranalu pa tadesak igwa ani bebzuhof bugib obhorem zat giwujet noed puk.",
    "bio": "Gigvaj guhcat pozuzpu ade ru no wugefla wifotu avocem izinocaru oninajsu pubupeko zefkobro doru leale gi nuuhoito evi. Rozrop ezucuhvak febgik ud ba as jec toija gid hucezu afe kulaw tehreeha tuzobsid. Nojdivrul dajoje nuslubwu ducopi zuh so mihe wek jad lusissin jumutfe cilu. Ca du go coove al fopgade botcaj ijifon dafak aneciswej efoav iduefuki gotpi hok muccoohu ud. Ze peukuvo so voh posgop tihanzi gefuku evamiwog hibris varej gojtadzup caapura cuotelu. Socwaga aboija ni de wema febtuc huhim lanet jepvaul dog jobu cil. Leziji ip za hat iklob uruokkas hi suc vagohaj ca raju kahera vimvefeh."
  },
  "apiKey": "7e7c5760ca0620730db3bdfac342480c83dbd12e1a6d1697a9372d03e63f3dd9",
  "currency": {
    "code": "MYR",
    "name": "Malaysia Ringgit"
  }
}